skinu/__init__.py
skinu/_internal/_global.py
skinu/_internal/_logs.py
skinu/core/datetime_utils.py
skinu/core/dict_utils.py
skinu/core/list_utils.py
skinu/core/pandas_utils.py
skinu/core/str_utils.py
skinu/performance/pump.py
skinu/sdms/__init__.py
skinu/sdms/_config.py
skinu/sdms/cb/__init__.py
skinu/sdms/cb/_base_document.py
skinu/sdms/cb/_base_recycle_document.py
skinu/sdms/cb/_base_single_document.py
skinu/sdms/cb/_manager.py
skinu/sdms/cb/_n1ql.py
skinu/sdms/cb/est/performance_log/__init__.py
skinu/sdms/cb/est/performance_log/_performance_log.py
skinu/sdms/cb/est/performance_log/_performance_status.py
skinu/sdms/cb/est/tag_est_log/__init__.py
skinu/sdms/cb/est/tag_est_log/_est_status.py
skinu/sdms/cb/est/tag_est_log/_tag_est_log.py
skinu/sdms/cb/message/master/__init__.py
skinu/sdms/cb/message/master/_request_message.py
skinu/sdms/cb/message/master/_request_message_comp.py
skinu/sdms/cb/message/master/_request_message_email.py
skinu/sdms/cb/message/master/_request_message_sms.py
skinu/sdms/cb/message/skadi/__init__.py
skinu/sdms/cb/message/skadi/_alarm_message.py
skinu/sdms/cb/message/skadi/_alarm_message_comp.py
skinu/sdms/cb/raw/lab/__init__.py
skinu/sdms/cb/raw/lab/_eai_lab_status.py
skinu/sdms/cb/raw/lab/_eai_lab_tag_status.py
skinu/sdms/cb/raw/lab/_lab.py
skinu/sdms/cb/raw/rst/__init__.py
skinu/sdms/cb/raw/rst/_rst.py
skinu/sdms/cb/raw/rst/_rtdb_status.py
skinu/sdms/cb/raw/rst/_tag_status.py
skinu/sdms/cb/raw_eai/skadi/__init__.py
skinu/sdms/cb/raw_eai/skadi/_eai_workorder_status.py
skinu/sdms/cb/raw_eai/skadi/_ocean_equip.py
skinu/sdms/cb/raw_eai/skadi/_sample_data.py
skinu/sdms/cb/raw_eai/skadi/_sample_equip.py
skinu/sdms/cb/raw_eai/skadi/_sample_point.py
skinu/sdms/cb/raw_eai/skadi/_sample_test_item.py
skinu/sdms/cb/raw_eai/skadi/_workorder.py
skinu/sdms/cb/ref/equip_ref/__init__.py
skinu/sdms/cb/ref/equip_ref/_ref_model.py
skinu/sdms/cb/skadi/common/__init__.py
skinu/sdms/cb/skadi/common/_board.py
skinu/sdms/cb/skadi/common/_board_attach_file.py
skinu-0.0.1.1.dist-info/METADATA
skinu-0.0.1.1.dist-info/WHEEL
skinu-0.0.1.1.dist-info/RECORD
