Metadata-Version: 2.1
Name: skinu
Version: 0.0.1.1
Summary: skadi support library package
License: MIT
Author: JeongHun Lee
Requires-Python: >=3.9,<4.0
Classifier: License :: OSI Approved :: MIT License
Classifier: Programming Language :: Python :: 3
Classifier: Programming Language :: Python :: 3.9
Classifier: Programming Language :: Python :: 3.10
Classifier: Programming Language :: Python :: 3.11
Requires-Dist: autopep8 (==2.0.1)
Requires-Dist: colorama (==0.4.6)
Requires-Dist: colorlog (>=6.7.0,<7.0.0)
Requires-Dist: couchbase (>=4.1.2,<5.0.0)
Requires-Dist: numpy (>=1.24.2,<2.0.0)
Requires-Dist: pandas (>=1.5.3,<2.0.0)
Requires-Dist: pycodestyle (>=2.10.0,<3.0.0)
Requires-Dist: python-dateutil (>=2.8.2,<3.0.0)
Requires-Dist: pytz (>=2022.7.1,<2023.0.0)
Requires-Dist: six (>=1.16.0,<2.0.0)
Requires-Dist: tomli (>=2.0.1,<3.0.0)
Requires-Dist: twine (>=4.0.2,<5.0.0)
